histlite/__init__.py
histlite/heal.py
histlite/termplot.py
histlite/version.py
histlite-2025.7.1.dist-info/METADATA
histlite-2025.7.1.dist-info/WHEEL
histlite-2025.7.1.dist-info/RECORD
