Metadata-Version: 2.4
Name: histlite
Version: 2025.7.1
Summary: A somewhat "lite" histogram library
Project-URL: Homepage, https://histlite.readthedocs.io/
Project-URL: Documentation, https://histlite.readthedocs.io/
Project-URL: Repository, https://github.com/zgana/histlite
Project-URL: Issues, https://github.com/zgana/histlite/issues
Author-email: Mike Richman <mike.d.richman@gmail.com>
Requires-Python: >=3.13
Requires-Dist: numpy
Requires-Dist: scipy
